robustness/__init__.py
robustness/attack_steps.py
robustness/attacker.py
robustness/data_augmentation.py
robustness/datasets.py
robustness/defaults.py
robustness/loaders.py
robustness/main.py
robustness/model_utils.py
robustness/train.py
robustness/cifar_models/__init__.py
robustness/cifar_models/densenet.py
robustness/cifar_models/inception.py
robustness/cifar_models/resnet.py
robustness/cifar_models/vgg.py
robustness/imagenet_models/__init__.py
robustness/imagenet_models/alexnet.py
robustness/imagenet_models/custom_modules.py
robustness/imagenet_models/densenet.py
robustness/imagenet_models/leaky_resnet.py
robustness/imagenet_models/resnet.py
robustness/imagenet_models/squeezenet.py
robustness/imagenet_models/vgg.py
robustness/imagenet_models/wide_resnet.py
robustness/tools/__init__.py
robustness/tools/breeds_helpers.py
robustness/tools/constants.py
robustness/tools/custom_modules.py
robustness/tools/folder.py
robustness/tools/helpers.py
robustness/tools/imagenet_helpers.py
robustness/tools/label_maps.py
robustness/tools/openimgs_helpers.py
robustness/tools/vis_tools.py
robustness-1.2.1.post2.dist-info/LICENSE.txt
robustness-1.2.1.post2.dist-info/METADATA
robustness-1.2.1.post2.dist-info/WHEEL
robustness-1.2.1.post2.dist-info/top_level.txt
robustness-1.2.1.post2.dist-info/RECORD
