Metadata-Version: 2.1
Name: robustness
Version: 1.2.1.post2
Summary: Tools for Robustness
Home-page: UNKNOWN
Author: MadryLab
Author-email: ailyas@mit.edu
License: MIT
Keywords: logging tools madrylab
Platform: UNKNOWN
Classifier: Development Status :: 4 - Beta
Classifier: Intended Audience :: Developers
Classifier: Topic :: Software Development :: Build Tools
Classifier: License :: OSI Approved :: MIT License
Classifier: Programming Language :: Python :: 3
Classifier: Programming Language :: Python :: 3.5
Classifier: Programming Language :: Python :: 3.6
Requires-Dist: tqdm
Requires-Dist: grpcio
Requires-Dist: psutil
Requires-Dist: gitpython
Requires-Dist: py3nvml
Requires-Dist: cox
Requires-Dist: scikit-learn
Requires-Dist: seaborn
Requires-Dist: torch
Requires-Dist: torchvision
Requires-Dist: pandas
Requires-Dist: numpy
Requires-Dist: scipy
Requires-Dist: GPUtil
Requires-Dist: dill
Requires-Dist: tensorboardX
Requires-Dist: tables
Requires-Dist: matplotlib
